common_check_widget/backend_lib/__init__.py
common_check_widget/backend_lib/py.typed
common_check_widget/backend_lib/_jsii/__init__.py
common_check_widget/backend_lib/_jsii/common-check-widget-backend-lib@1.0.5.jsii.tgz
common_check_widget.backend_lib-1.0.5.dist-info/LICENSE
common_check_widget.backend_lib-1.0.5.dist-info/METADATA
common_check_widget.backend_lib-1.0.5.dist-info/WHEEL
common_check_widget.backend_lib-1.0.5.dist-info/top_level.txt
common_check_widget.backend_lib-1.0.5.dist-info/RECORD
