Metadata-Version: 2.1
Name: common-check-widget.backend-lib
Version: 1.0.5
Summary: UNKNOWN
Home-page: https://gitlab.com/common-check-widget-backend-lib#readme
Author: Chai Jian Wei<jianwei.c@affinidi.com>
License: MIT-0
Project-URL: Source, https://gitlab.com/common-check-widget-backend-lib.git
Platform: UNKNOWN
Classifier: Intended Audience :: Developers
Classifier: Operating System :: OS Independent
Classifier: Programming Language :: JavaScript
Classifier: Programming Language :: Python :: 3 :: Only
Classifier: Programming Language :: Python :: 3.6
Classifier: Programming Language :: Python :: 3.7
Classifier: Programming Language :: Python :: 3.8
Classifier: Programming Language :: Python :: 3.9
Classifier: Typing :: Typed
Classifier: License :: OSI Approved
Requires-Python: >=3.6
Requires-Dist: jsii (<2.0.0,>=1.32.0)
Requires-Dist: publication (>=0.0.3)
